papex/__init__.py
papex/fetch_strategies.py
papex/generic_adapter.py
papex/paperObj.py
papex/provider_config.py
papex-0.0.4.dist-info/METADATA
papex-0.0.4.dist-info/WHEEL
papex-0.0.4.dist-info/top_level.txt
papex-0.0.4.dist-info/RECORD
