Metadata-Version: 2.4
Name: papex
Version: 0.0.4
Summary: A library for fetching and normalizing academic papers from various providers (Elsevier, arXiv, PRISM, etc.)
Home-page: https://github.com/maryamSayagh/PapEx
Author: maryamSayagh
Author-email: maryamsayagho@gmail.com
Requires-Python: >=3.7
Requires-Dist: requests>=2.25.1
Requires-Dist: orjson>=3.6.4
Requires-Dist: lxml>=4.6.3
Requires-Dist: arxiv>=1.4.8
Dynamic: author
Dynamic: author-email
Dynamic: description
Dynamic: description-content-type
Dynamic: home-page
Dynamic: requires-dist
Dynamic: requires-python
Dynamic: summary
